[{"id":1,"gender":"Male","user_name":"bwooff0","organization":"Jamia","date":"2021-05-25 10:45:49","phone_number":"774-425-5789","children":1,"bvn":"7205636744","gurantor":"Isac Petchey","gurantor_email":"bwooff0@freewebs.com","user":"Bord Wooff","user_email":"bwooff0@hibu.com"},
    {"id":2,"gender":"Male","user_name":"edate1","organization":"Zazio","date":"2021-05-28 04:21:36","phone_number":"931-702-2562","children":2,"bvn":"2466227398","gurantor":"Hersh Issard","gurantor_email":"edate1@house.gov","user":"Emanuel Date","user_email":"edate1@netlog.com"},
    {"id":3,"gender":"Female","user_name":"tleyburn2","organization":"Yambee","date":"2021-09-11 08:01:52","phone_number":"686-278-3877","children":3,"bvn":"8071665185","gurantor":"Constance Coll","gurantor_email":"tleyburn2@blogger.com","user":"Terry Leyburn","user_email":"tleyburn2@nationalgeographic.com"},
    {"id":4,"gender":"Polygender","user_name":"fgrene3","organization":"Podcat","date":"2021-07-02 19:23:38","phone_number":"177-666-7398","children":4,"bvn":"4760092587","gurantor":"Marcus Crier","gurantor_email":"fgrene3@ycombinator.com","user":"Floyd Grene","user_email":"fgrene3@google.com.au"},
    {"id":5,"gender":"Female","user_name":"ispiteri4","organization":"Riffwire","date":"2021-05-24 23:30:49","phone_number":"199-879-7878","children":5,"bvn":"3833686855","gurantor":"Jonell Simacek","gurantor_email":"ispiteri4@ucla.edu","user":"Imojean Spiteri","user_email":"ispiteri4@ameblo.jp"},
    {"id":6,"gender":"Male","user_name":"hmelville5","organization":"Latz","date":"2022-01-12 07:23:53","phone_number":"790-890-5272","children":6,"bvn":"8177931466","gurantor":"Yank Evanson","gurantor_email":"hmelville5@lulu.com","user":"Holt Melville","user_email":"hmelville5@deliciousdays.com"},
    {"id":7,"gender":"Female","user_name":"cbransden6","organization":"Browseblab","date":"2021-12-20 20:05:40","phone_number":"155-657-6446","children":7,"bvn":"4116256285","gurantor":"Aurlie Pinnigar","gurantor_email":"cbransden6@slate.com","user":"Casandra Bransden","user_email":"cbransden6@wunderground.com"},
    {"id":8,"gender":"Male","user_name":"wbamforth7","organization":"Oyoba","date":"2021-09-29 17:11:47","phone_number":"632-444-0027","children":8,"bvn":"5002595049","gurantor":"Woodman McCord","gurantor_email":"wbamforth7@booking.com","user":"Ward Bamforth","user_email":"wbamforth7@state.gov"},
    {"id":9,"gender":"Non-binary","user_name":"hpostan8","organization":"Chatterbridge","date":"2022-03-23 06:19:15","phone_number":"573-540-4890","children":9,"bvn":"2133320598","gurantor":"Clarabelle Brandle","gurantor_email":"hpostan8@wufoo.com","user":"Hewitt Postan","user_email":"hpostan8@histats.com"},
    {"id":10,"gender":"Female","user_name":"gogger9","organization":"Fadeo","date":"2022-04-07 16:12:03","phone_number":"913-655-7655","children":10,"bvn":"0480162700","gurantor":"Kelila Antham","gurantor_email":"gogger9@furl.net","user":"Gus Ogger","user_email":"gogger9@theglobeandmail.com"},
    {"id":11,"gender":"Male","user_name":"efisbeya","organization":"Rooxo","date":"2021-07-25 00:41:17","phone_number":"316-651-6892","children":11,"bvn":"7864744370","gurantor":"Grove Harbard","gurantor_email":"efisbeya@mashable.com","user":"Elton Fisbey","user_email":"efisbeya@redcross.org"},
    {"id":12,"gender":"Female","user_name":"dpickerb","organization":"Dabfeed","date":"2021-06-03 16:57:06","phone_number":"286-208-4610","children":12,"bvn":"5006600721","gurantor":"Gertruda Bolland","gurantor_email":"dpickerb@constantcontact.com","user":"Desdemona Picker","user_email":"dpickerb@mediafire.com"},
    {"id":13,"gender":"Male","user_name":"jgrishelyovc","organization":"Youspan","date":"2021-05-27 00:28:54","phone_number":"605-452-5585","children":13,"bvn":"9515405084","gurantor":"Jarvis Ebi","gurantor_email":"jgrishelyovc@gmpg.org","user":"Jule Grishelyov","user_email":"jgrishelyovc@tumblr.com"},
    {"id":14,"gender":"Female","user_name":"dlourencod","organization":"Photobean","date":"2021-10-29 05:34:14","phone_number":"928-177-3823","children":14,"bvn":"6330483345","gurantor":"Zahara Hibbart","gurantor_email":"dlourencod@google.com.hk","user":"Dodie Lourenco","user_email":"dlourencod@google.com"},
    {"id":15,"gender":"Female","user_name":"smalte","organization":"Bubblemix","date":"2021-12-17 14:45:02","phone_number":"280-600-1141","children":15,"bvn":"9089628347","gurantor":"Tressa Laight","gurantor_email":"smalte@friendfeed.com","user":"Sibeal Malt","user_email":"smalte@businessinsider.com"},
    {"id":16,"gender":"Male","user_name":"dcorsonf","organization":"Livetube","date":"2021-11-20 20:40:20","phone_number":"441-287-2969","children":16,"bvn":"1156780632","gurantor":"Trstram McLelland","gurantor_email":"dcorsonf@economist.com","user":"Darbee Corson","user_email":"dcorsonf@arstechnica.com"},
    {"id":17,"gender":"Male","user_name":"abladong","organization":"Latz","date":"2022-01-21 00:14:27","phone_number":"281-619-2436","children":17,"bvn":"6877227220","gurantor":"Teador Birrel","gurantor_email":"abladong@gnu.org","user":"Aristotle Bladon","user_email":"abladong@washingtonpost.com"},
    {"id":18,"gender":"Genderqueer","user_name":"tklessh","organization":"Wikizz","date":"2022-02-20 23:43:07","phone_number":"716-934-6361","children":18,"bvn":"9708081655","gurantor":"Alverta Kingescot","gurantor_email":"tklessh@foxnews.com","user":"Timothea Kless","user_email":"tklessh@upenn.edu"},
    {"id":19,"gender":"Female","user_name":"msakeri","organization":"Feednation","date":"2022-01-06 01:20:10","phone_number":"452-211-3344","children":19,"bvn":"0881991244","gurantor":"Adelaida Rickersy","gurantor_email":"msakeri@mlb.com","user":"Modestine Saker","user_email":"msakeri@acquirethisname.com"},
    {"id":20,"gender":"Male","user_name":"sdallicottj","organization":"Npath","date":"2022-02-19 02:05:13","phone_number":"331-459-6716","children":20,"bvn":"7684360302","gurantor":"Bartolemo Penhaligon","gurantor_email":"sdallicottj@apache.org","user":"Salmon Dallicott","user_email":"sdallicottj@wordpress.com"},
    {"id":21,"gender":"Male","user_name":"mscortonk","organization":"Realblab","date":"2021-07-10 16:56:43","phone_number":"224-904-7630","children":21,"bvn":"7390914238","gurantor":"Tomlin Cadwallader","gurantor_email":"mscortonk@mail.ru","user":"Maxwell Scorton","user_email":"mscortonk@aol.com"},
    {"id":22,"gender":"Non-binary","user_name":"epickrelll","organization":"Thoughtmix","date":"2021-11-17 04:47:24","phone_number":"636-884-4286","children":22,"bvn":"9475573682","gurantor":"Elianora Cuphus","gurantor_email":"epickrelll@china.com.cn","user":"Elisha Pickrell","user_email":"epickrelll@amazon.com"},
    {"id":23,"gender":"Female","user_name":"cmussardm","organization":"Brightbean","date":"2021-08-10 22:59:47","phone_number":"819-506-4449","children":23,"bvn":"1924888769","gurantor":"Heath Girth","gurantor_email":"cmussardm@bluehost.com","user":"Clarine Mussard","user_email":"cmussardm@tmall.com"},
    {"id":24,"gender":"Male","user_name":"lprattingtonn","organization":"Jabbersphere","date":"2021-11-11 00:43:56","phone_number":"758-715-4906","children":24,"bvn":"5625839298","gurantor":"Georgi Cornelissen","gurantor_email":"lprattingtonn@toplist.cz","user":"Lindy Prattington","user_email":"lprattingtonn@who.int"},
    {"id":25,"gender":"Female","user_name":"hbalsillieo","organization":"Gigaclub","date":"2022-03-12 12:47:18","phone_number":"482-749-8669","children":25,"bvn":"3848100746","gurantor":"Domini Work","gurantor_email":"hbalsillieo@hibu.com","user":"Heida Balsillie","user_email":"hbalsillieo@msu.edu"},
    {"id":26,"gender":"Female","user_name":"cpherpsp","organization":"Thoughtsphere","date":"2022-03-21 04:45:28","phone_number":"726-976-3585","children":26,"bvn":"7806445455","gurantor":"Evey Scolli","gurantor_email":"cpherpsp@vkontakte.ru","user":"Chelsae Pherps","user_email":"cpherpsp@nsw.gov.au"},
    {"id":27,"gender":"Male","user_name":"mkearleyq","organization":"Twiyo","date":"2021-12-23 13:16:31","phone_number":"843-266-6315","children":27,"bvn":"8141319116","gurantor":"Iorgo Gullane","gurantor_email":"mkearleyq@xrea.com","user":"Moritz Kearley","user_email":"mkearleyq@baidu.com"},
    {"id":28,"gender":"Male","user_name":"ghamilr","organization":"Demizz","date":"2022-05-06 19:54:44","phone_number":"981-416-6457","children":28,"bvn":"8852794239","gurantor":"Rick Simcoe","gurantor_email":"ghamilr@tmall.com","user":"Gibby Hamil","user_email":"ghamilr@pbs.org"},
    {"id":29,"gender":"Male","user_name":"npeisers","organization":"Brainverse","date":"2022-04-08 07:55:48","phone_number":"653-814-6928","children":29,"bvn":"2422132251","gurantor":"Colan Raddish","gurantor_email":"npeisers@wiley.com","user":"Nichols Peiser","user_email":"npeisers@hostgator.com"},
    {"id":30,"gender":"Male","user_name":"rmagistert","organization":"Vinte","date":"2021-09-15 02:38:16","phone_number":"317-666-2345","children":30,"bvn":"5554136362","gurantor":"Terrence Gallichiccio","gurantor_email":"rmagistert@uiuc.edu","user":"Rafferty Magister","user_email":"rmagistert@ox.ac.uk"},
    {"id":31,"gender":"Female","user_name":"rmordanu","organization":"Chatterbridge","date":"2022-01-26 10:12:25","phone_number":"532-603-8445","children":31,"bvn":"5647349129","gurantor":"Ursuline Helkin","gurantor_email":"rmordanu@tinypic.com","user":"Rubi Mordan","user_email":"rmordanu@artisteer.com"},
    {"id":32,"gender":"Male","user_name":"wgenikev","organization":"Fadeo","date":"2022-01-26 04:43:10","phone_number":"261-639-8684","children":32,"bvn":"4317051710","gurantor":"Kippar Saiz","gurantor_email":"wgenikev@google.fr","user":"Willie Genike","user_email":"wgenikev@ovh.net"},
    {"id":33,"gender":"Female","user_name":"hcunnahw","organization":"Flipbug","date":"2022-03-01 15:21:31","phone_number":"648-430-8779","children":33,"bvn":"1010264753","gurantor":"Margie Gaiter","gurantor_email":"hcunnahw@de.vu","user":"Hilary Cunnah","user_email":"hcunnahw@sitemeter.com"},
    {"id":34,"gender":"Female","user_name":"sjollyex","organization":"Quamba","date":"2021-07-07 08:14:27","phone_number":"830-448-1758","children":34,"bvn":"6178611390","gurantor":"Elna Wreiford","gurantor_email":"sjollyex@nifty.com","user":"Sheilah Jollye","user_email":"sjollyex@miibeian.gov.cn"},
    {"id":35,"gender":"Female","user_name":"jbradnockey","organization":"Linklinks","date":"2021-05-24 17:01:58","phone_number":"185-272-1065","children":35,"bvn":"3210090548","gurantor":"Valma Fritschel","gurantor_email":"jbradnockey@acquirethisname.com","user":"Jonis Bradnocke","user_email":"jbradnockey@de.vu"},
    {"id":36,"gender":"Female","user_name":"rsimcockz","organization":"Browsebug","date":"2021-12-03 08:02:01","phone_number":"762-718-3074","children":36,"bvn":"9562320731","gurantor":"Elnora Gwillyam","gurantor_email":"rsimcockz@phoca.cz","user":"Raychel Simcock","user_email":"rsimcockz@macromedia.com"},
    {"id":37,"gender":"Female","user_name":"ktrowsdall10","organization":"Vinder","date":"2021-10-06 12:56:55","phone_number":"157-108-9045","children":37,"bvn":"2764670354","gurantor":"Perl Yegorshin","gurantor_email":"ktrowsdall10@google.com.hk","user":"Kerrill Trowsdall","user_email":"ktrowsdall10@e-recht24.de"},
    {"id":38,"gender":"Female","user_name":"bnardoni11","organization":"JumpXS","date":"2021-06-17 10:57:17","phone_number":"970-276-5674","children":38,"bvn":"5655485370","gurantor":"Ester Tungay","gurantor_email":"bnardoni11@hatena.ne.jp","user":"Blancha Nardoni","user_email":"bnardoni11@spotify.com"},
    {"id":39,"gender":"Female","user_name":"mclutterham12","organization":"Realbridge","date":"2021-08-19 15:44:47","phone_number":"914-209-7898","children":39,"bvn":"5424102115","gurantor":"Janenna Matskevich","gurantor_email":"mclutterham12@yahoo.com","user":"Mariel Clutterham","user_email":"mclutterham12@china.com.cn"},
    {"id":40,"gender":"Female","user_name":"tmowsley13","organization":"Divape","date":"2021-06-24 20:48:14","phone_number":"870-667-3293","children":40,"bvn":"6957536491","gurantor":"Sibby Ismead","gurantor_email":"tmowsley13@paypal.com","user":"Tabbatha Mowsley","user_email":"tmowsley13@hibu.com"},
    {"id":41,"gender":"Female","user_name":"jgerok14","organization":"Dabvine","date":"2021-10-16 19:02:26","phone_number":"858-955-7691","children":41,"bvn":"4630692223","gurantor":"Tommie Willingam","gurantor_email":"jgerok14@weather.com","user":"Jennine Gerok","user_email":"jgerok14@yelp.com"},
    {"id":42,"gender":"Polygender","user_name":"nbarnwill15","organization":"Yodel","date":"2022-04-09 00:43:24","phone_number":"751-129-3414","children":42,"bvn":"4385680442","gurantor":"Elana Whitton","gurantor_email":"nbarnwill15@desdev.cn","user":"Norris Barnwill","user_email":"nbarnwill15@shop-pro.jp"},
    {"id":43,"gender":"Female","user_name":"dgilstoun16","organization":"Twimm","date":"2021-05-14 07:25:21","phone_number":"324-931-0317","children":43,"bvn":"7434807687","gurantor":"Charyl Huntley","gurantor_email":"dgilstoun16@engadget.com","user":"Dacia Gilstoun","user_email":"dgilstoun16@addthis.com"},
    {"id":44,"gender":"Female","user_name":"tpinch17","organization":"Yakidoo","date":"2021-10-04 04:20:05","phone_number":"545-736-7574","children":44,"bvn":"2975007388","gurantor":"Kathe Cogin","gurantor_email":"tpinch17@phoca.cz","user":"Tiffie Pinch","user_email":"tpinch17@is.gd"},
    {"id":45,"gender":"Male","user_name":"croyan18","organization":"Gabcube","date":"2021-11-09 04:55:11","phone_number":"514-246-5328","children":45,"bvn":"6092841959","gurantor":"Waylen Moncreiffe","gurantor_email":"croyan18@amazon.co.jp","user":"Cos Royan","user_email":"croyan18@miibeian.gov.cn"},
    {"id":46,"gender":"Male","user_name":"bpauleau19","organization":"Yakijo","date":"2021-09-01 06:56:07","phone_number":"474-322-0057","children":46,"bvn":"0656220783","gurantor":"Thorvald Niesegen","gurantor_email":"bpauleau19@myspace.com","user":"Brnaby Pauleau","user_email":"bpauleau19@go.com"},
    {"id":47,"gender":"Male","user_name":"ablacklawe1a","organization":"Flipbug","date":"2022-03-15 02:52:29","phone_number":"365-400-2075","children":47,"bvn":"0907800920","gurantor":"Bryce Fairburn","gurantor_email":"ablacklawe1a@oaic.gov.au","user":"Arnie Blacklawe","user_email":"ablacklawe1a@jimdo.com"},
    {"id":48,"gender":"Male","user_name":"lcadore1b","organization":"Meevee","date":"2021-06-29 03:20:52","phone_number":"508-860-8160","children":48,"bvn":"6156708502","gurantor":"Olivier Abrahmovici","gurantor_email":"lcadore1b@stanford.edu","user":"Laurens Cadore","user_email":"lcadore1b@is.gd"},
    {"id":49,"gender":"Male","user_name":"tphythean1c","organization":"Flipstorm","date":"2021-08-12 05:02:01","phone_number":"483-795-1552","children":49,"bvn":"3025673249","gurantor":"Bil Antuoni","gurantor_email":"tphythean1c@unc.edu","user":"Thane Phythean","user_email":"tphythean1c@illinois.edu"},
    {"id":50,"gender":"Female","user_name":"bledgley1d","organization":"Realcube","date":"2021-09-29 22:28:47","phone_number":"969-943-5318","children":50,"bvn":"2179220375","gurantor":"Doretta Gillyett","gurantor_email":"bledgley1d@dailymotion.com","user":"Bianka Ledgley","user_email":"bledgley1d@yahoo.co.jp"},
    {"id":51,"gender":"Female","user_name":"kmillership1e","organization":"Kwinu","date":"2022-05-07 07:10:51","phone_number":"170-131-4945","children":51,"bvn":"1973514605","gurantor":"Fania Kindred","gurantor_email":"kmillership1e@squidoo.com","user":"Ketty Millership","user_email":"kmillership1e@hhs.gov"},
    {"id":52,"gender":"Male","user_name":"vde1f","organization":"Mymm","date":"2021-05-30 09:08:07","phone_number":"744-189-5643","children":52,"bvn":"7133049414","gurantor":"Cchaddie Ankers","gurantor_email":"vde1f@irs.gov","user":"Vladimir de Amaya","user_email":"vde1f@fc2.com"},
    {"id":53,"gender":"Male","user_name":"lcapponeer1g","organization":"Yotz","date":"2021-10-07 04:29:04","phone_number":"953-673-3077","children":53,"bvn":"7722881459","gurantor":"Roderich Yeardsley","gurantor_email":"lcapponeer1g@slate.com","user":"Lonny Capponeer","user_email":"lcapponeer1g@ft.com"},
    {"id":54,"gender":"Male","user_name":"zcannicott1h","organization":"Twinder","date":"2022-02-01 09:09:50","phone_number":"448-132-0957","children":54,"bvn":"7627708818","gurantor":"Norrie Tourle","gurantor_email":"zcannicott1h@istockphoto.com","user":"Zane Cannicott","user_email":"zcannicott1h@privacy.gov.au"},
    {"id":55,"gender":"Female","user_name":"hendersby1i","organization":"Bluezoom","date":"2022-01-31 04:00:28","phone_number":"306-895-3014","children":55,"bvn":"4832055984","gurantor":"Shelby Yve","gurantor_email":"hendersby1i@princeton.edu","user":"Hildagard Endersby","user_email":"hendersby1i@wordpress.org"},
    {"id":56,"gender":"Male","user_name":"phannis1j","organization":"Realblab","date":"2021-09-30 18:00:38","phone_number":"378-797-3307","children":56,"bvn":"4606101806","gurantor":"Caryl Cammish","gurantor_email":"phannis1j@rambler.ru","user":"Pattin Hannis","user_email":"phannis1j@mayoclinic.com"},
    {"id":57,"gender":"Male","user_name":"flowis1k","organization":"Blognation","date":"2022-02-19 11:32:20","phone_number":"876-752-6120","children":57,"bvn":"7649886816","gurantor":"Carlie Ivery","gurantor_email":"flowis1k@networksolutions.com","user":"Freemon Lowis","user_email":"flowis1k@latimes.com"},
    {"id":58,"gender":"Female","user_name":"rbertie1l","organization":"Agivu","date":"2021-12-25 14:03:32","phone_number":"206-600-4065","children":58,"bvn":"5866917289","gurantor":"Arlette Planks","gurantor_email":"rbertie1l@exblog.jp","user":"Robinett Bertie","user_email":"rbertie1l@tinyurl.com"},
    {"id":59,"gender":"Female","user_name":"dpurcell1m","organization":"Ooba","date":"2022-04-26 21:43:43","phone_number":"929-412-2267","children":59,"bvn":"3212815833","gurantor":"Carena Chilton","gurantor_email":"dpurcell1m@qq.com","user":"Danella Purcell","user_email":"dpurcell1m@drupal.org"},
    {"id":60,"gender":"Female","user_name":"rketley1n","organization":"Babblestorm","date":"2021-06-12 21:10:32","phone_number":"697-952-2614","children":60,"bvn":"7964188143","gurantor":"Bella Amsden","gurantor_email":"rketley1n@rediff.com","user":"Rena Ketley","user_email":"rketley1n@friendfeed.com"},
    {"id":61,"gender":"Male","user_name":"kzamorano1o","organization":"Shufflebeat","date":"2021-09-16 04:40:14","phone_number":"701-371-3755","children":61,"bvn":"4181431576","gurantor":"Ramsey Simmins","gurantor_email":"kzamorano1o@guardian.co.uk","user":"Kenny Zamorano","user_email":"kzamorano1o@wunderground.com"},
    {"id":62,"gender":"Female","user_name":"mkubica1p","organization":"Brainbox","date":"2021-06-16 08:05:59","phone_number":"822-208-2486","children":62,"bvn":"2467935302","gurantor":"Mercy Desport","gurantor_email":"mkubica1p@seattletimes.com","user":"Mariejeanne Kubica","user_email":"mkubica1p@icq.com"},
    {"id":63,"gender":"Female","user_name":"lcashman1q","organization":"Feedbug","date":"2022-02-26 05:03:29","phone_number":"511-840-0844","children":63,"bvn":"5536964615","gurantor":"Analiese Carrigan","gurantor_email":"lcashman1q@un.org","user":"Lara Cashman","user_email":"lcashman1q@mapy.cz"},
    {"id":64,"gender":"Male","user_name":"emullaney1r","organization":"Gigabox","date":"2021-06-06 06:29:11","phone_number":"674-163-1674","children":64,"bvn":"6768566784","gurantor":"Isaac Lillecrap","gurantor_email":"emullaney1r@friendfeed.com","user":"Elton Mullaney","user_email":"emullaney1r@yale.edu"},
    {"id":65,"gender":"Female","user_name":"ebiddell1s","organization":"Gigazoom","date":"2021-08-31 22:15:39","phone_number":"794-741-1598","children":65,"bvn":"9181992602","gurantor":"Ealasaid Gueny","gurantor_email":"ebiddell1s@studiopress.com","user":"Eleanore Biddell","user_email":"ebiddell1s@telegraph.co.uk"},
    {"id":66,"gender":"Female","user_name":"pescott1t","organization":"Eare","date":"2022-02-08 14:29:26","phone_number":"127-678-7833","children":66,"bvn":"4414463726","gurantor":"Jorrie Sollowaye","gurantor_email":"pescott1t@plala.or.jp","user":"Patti Escott","user_email":"pescott1t@about.com"},
    {"id":67,"gender":"Female","user_name":"mgogarty1u","organization":"Photobug","date":"2021-09-25 13:41:10","phone_number":"510-948-0735","children":67,"bvn":"8050584879","gurantor":"Barbabra Bygate","gurantor_email":"mgogarty1u@joomla.org","user":"Mariya Gogarty","user_email":"mgogarty1u@vistaprint.com"},
    {"id":68,"gender":"Female","user_name":"abroggio1v","organization":"Gevee","date":"2021-10-03 06:38:39","phone_number":"389-369-2868","children":68,"bvn":"6565753121","gurantor":"Horatia Bossons","gurantor_email":"abroggio1v@domainmarket.com","user":"Allyce Broggio","user_email":"abroggio1v@tuttocitta.it"},
    {"id":69,"gender":"Male","user_name":"rsisson1w","organization":"Vipe","date":"2021-12-19 00:58:21","phone_number":"105-641-6563","children":69,"bvn":"5891001500","gurantor":"Sumner Dressel","gurantor_email":"rsisson1w@addtoany.com","user":"Richie Sisson","user_email":"rsisson1w@mapquest.com"},
    {"id":70,"gender":"Bigender","user_name":"pmcguffog1x","organization":"Twimbo","date":"2022-03-30 22:16:20","phone_number":"120-398-0705","children":70,"bvn":"4314767324","gurantor":"Royall McCrann","gurantor_email":"pmcguffog1x@moonfruit.com","user":"Page McGuffog","user_email":"pmcguffog1x@typepad.com"},
    {"id":71,"gender":"Male","user_name":"elowndsbrough1y","organization":"Twitterbridge","date":"2021-09-12 21:01:31","phone_number":"102-288-3826","children":71,"bvn":"4322407900","gurantor":"Garry Beaushaw","gurantor_email":"elowndsbrough1y@wikimedia.org","user":"Elihu Lowndsbrough","user_email":"elowndsbrough1y@usatoday.com"},
    {"id":72,"gender":"Bigender","user_name":"skalker1z","organization":"Lajo","date":"2021-09-13 13:34:50","phone_number":"998-106-4930","children":72,"bvn":"4857762129","gurantor":"Xavier Dyott","gurantor_email":"skalker1z@google.de","user":"Sanderson Kalker","user_email":"skalker1z@mozilla.com"},
    {"id":73,"gender":"Male","user_name":"brabjohn20","organization":"Jaxbean","date":"2021-09-09 19:38:29","phone_number":"270-498-9839","children":73,"bvn":"8821410404","gurantor":"Lion Hedin","gurantor_email":"brabjohn20@examiner.com","user":"Berkeley Rabjohn","user_email":"brabjohn20@symantec.com"},
    {"id":74,"gender":"Male","user_name":"jfeaver21","organization":"Feedbug","date":"2021-05-14 17:07:33","phone_number":"586-993-0076","children":74,"bvn":"4103956178","gurantor":"Ambrose Belf","gurantor_email":"jfeaver21@tinyurl.com","user":"Jacky Feaver","user_email":"jfeaver21@google.cn"},
    {"id":75,"gender":"Female","user_name":"jloncaster22","organization":"Twinder","date":"2021-09-21 01:36:21","phone_number":"484-303-0244","children":75,"bvn":"2359546198","gurantor":"Donetta Suthworth","gurantor_email":"jloncaster22@bbc.co.uk","user":"Jeannette Loncaster","user_email":"jloncaster22@sciencedirect.com"},
    {"id":76,"gender":"Male","user_name":"rwoolbrook23","organization":"Agimba","date":"2022-03-22 01:39:34","phone_number":"744-805-5493","children":76,"bvn":"9399754189","gurantor":"Shurwood Gallagher","gurantor_email":"rwoolbrook23@prnewswire.com","user":"Ryon Woolbrook","user_email":"rwoolbrook23@github.io"},
    {"id":77,"gender":"Male","user_name":"plimer24","organization":"Voonder","date":"2021-07-13 07:34:53","phone_number":"453-307-7351","children":77,"bvn":"2326556054","gurantor":"Grantley Innett","gurantor_email":"plimer24@aboutads.info","user":"Patrick Limer","user_email":"plimer24@dion.ne.jp"},
    {"id":78,"gender":"Male","user_name":"rbuddington25","organization":"Brainbox","date":"2021-05-21 20:35:53","phone_number":"644-476-6897","children":78,"bvn":"1950957039","gurantor":"Brandtr Dockreay","gurantor_email":"rbuddington25@baidu.com","user":"Rubin Buddington","user_email":"rbuddington25@hatena.ne.jp"},
    {"id":79,"gender":"Male","user_name":"lchitson26","organization":"Demimbu","date":"2021-09-04 19:12:53","phone_number":"546-547-8791","children":79,"bvn":"2265636258","gurantor":"Garth Koenraad","gurantor_email":"lchitson26@trellian.com","user":"Lorry Chitson","user_email":"lchitson26@canalblog.com"},
    {"id":80,"gender":"Male","user_name":"acomben27","organization":"Yakidoo","date":"2022-02-16 06:00:35","phone_number":"518-620-4424","children":80,"bvn":"5845811880","gurantor":"Quill Delamere","gurantor_email":"acomben27@parallels.com","user":"Alano Comben","user_email":"acomben27@macromedia.com"},
    {"id":81,"gender":"Male","user_name":"awherry28","organization":"Jatri","date":"2021-07-09 00:10:49","phone_number":"312-173-7111","children":81,"bvn":"9296917476","gurantor":"Hodge Haet","gurantor_email":"awherry28@paginegialle.it","user":"Aymer Wherry","user_email":"awherry28@netscape.com"},
    {"id":82,"gender":"Female","user_name":"dteasdale29","organization":"Demimbu","date":"2021-06-03 23:11:17","phone_number":"481-291-1367","children":82,"bvn":"4632104930","gurantor":"Lauryn Heady","gurantor_email":"dteasdale29@sourceforge.net","user":"Dorelia Teasdale","user_email":"dteasdale29@tripadvisor.com"},
    {"id":83,"gender":"Female","user_name":"wheart2a","organization":"Vimbo","date":"2022-01-28 07:22:26","phone_number":"243-289-8515","children":83,"bvn":"6236543747","gurantor":"Vannie Bachelar","gurantor_email":"wheart2a@hibu.com","user":"Winifred Heart","user_email":"wheart2a@about.me"},
    {"id":84,"gender":"Male","user_name":"ggraves2b","organization":"Photobean","date":"2022-03-29 20:31:55","phone_number":"869-308-0314","children":84,"bvn":"5625275505","gurantor":"Sylas Pulteneye","gurantor_email":"ggraves2b@jugem.jp","user":"Goddart Graves","user_email":"ggraves2b@squidoo.com"},
    {"id":85,"gender":"Female","user_name":"pwickenden2c","organization":"Zoomlounge","date":"2021-10-29 17:44:35","phone_number":"946-609-8504","children":85,"bvn":"2207762548","gurantor":"Dominga Emlin","gurantor_email":"pwickenden2c@mozilla.com","user":"Patty Wickenden","user_email":"pwickenden2c@merriam-webster.com"},
    {"id":86,"gender":"Non-binary","user_name":"mgoude2d","organization":"Izio","date":"2022-04-20 11:50:20","phone_number":"959-673-7750","children":86,"bvn":"3064161687","gurantor":"Darrel Petr","gurantor_email":"mgoude2d@vkontakte.ru","user":"Marcello Goude","user_email":"mgoude2d@ow.ly"},
    {"id":87,"gender":"Male","user_name":"qstaite2e","organization":"Photojam","date":"2021-11-07 20:50:10","phone_number":"878-777-1239","children":87,"bvn":"1384268480","gurantor":"Casper Danko","gurantor_email":"qstaite2e@examiner.com","user":"Quint Staite","user_email":"qstaite2e@china.com.cn"},
    {"id":88,"gender":"Female","user_name":"ccragg2f","organization":"Katz","date":"2021-09-22 02:27:40","phone_number":"822-613-7033","children":88,"bvn":"1628107170","gurantor":"Dulcea Leguay","gurantor_email":"ccragg2f@hc360.com","user":"Chanda Cragg","user_email":"ccragg2f@blogs.com"},
    {"id":89,"gender":"Male","user_name":"rwinchurst2g","organization":"Tavu","date":"2021-11-03 18:10:26","phone_number":"141-792-5216","children":89,"bvn":"4762303879","gurantor":"George Brusby","gurantor_email":"rwinchurst2g@woothemes.com","user":"Roderic Winchurst","user_email":"rwinchurst2g@ftc.gov"},
    {"id":90,"gender":"Female","user_name":"vragg2h","organization":"Brightdog","date":"2021-06-02 18:04:48","phone_number":"380-855-4808","children":90,"bvn":"4167384132","gurantor":"Robbi Gilroy","gurantor_email":"vragg2h@cam.ac.uk","user":"Vanny Ragg","user_email":"vragg2h@imdb.com"},
    {"id":91,"gender":"Male","user_name":"areightley2i","organization":"Linktype","date":"2021-10-12 03:31:43","phone_number":"868-605-3351","children":91,"bvn":"3576146016","gurantor":"Lek Haggus","gurantor_email":"areightley2i@reference.com","user":"Alford Reightley","user_email":"areightley2i@ning.com"},
    {"id":92,"gender":"Male","user_name":"abardill2j","organization":"Meeveo","date":"2021-09-05 20:17:13","phone_number":"768-692-1776","children":92,"bvn":"0242135714","gurantor":"Orville Thredder","gurantor_email":"abardill2j@t.co","user":"Allayne Bardill","user_email":"abardill2j@usda.gov"},
    {"id":93,"gender":"Non-binary","user_name":"kmusprat2k","organization":"Skajo","date":"2022-04-20 08:18:38","phone_number":"568-479-1825","children":93,"bvn":"0263903745","gurantor":"Adriaens McGettigan","gurantor_email":"kmusprat2k@mayoclinic.com","user":"Kathrine Musprat","user_email":"kmusprat2k@dedecms.com"},
    {"id":94,"gender":"Male","user_name":"srowesby2l","organization":"Centimia","date":"2022-02-12 03:35:32","phone_number":"568-856-9331","children":94,"bvn":"4896797019","gurantor":"Hazlett Germon","gurantor_email":"srowesby2l@topsy.com","user":"Saleem Rowesby","user_email":"srowesby2l@usnews.com"},
    {"id":95,"gender":"Male","user_name":"nbees2m","organization":"Blognation","date":"2021-06-16 05:46:02","phone_number":"747-921-9660","children":95,"bvn":"1600537383","gurantor":"Sauncho Tern","gurantor_email":"nbees2m@aol.com","user":"Neddy Bees","user_email":"nbees2m@webs.com"},
    {"id":96,"gender":"Male","user_name":"fsegrott2n","organization":"Roombo","date":"2021-12-27 03:11:17","phone_number":"731-670-0079","children":96,"bvn":"6823582685","gurantor":"Rudolf Gumme","gurantor_email":"fsegrott2n@bigcartel.com","user":"Frasco Segrott","user_email":"fsegrott2n@gravatar.com"},
    {"id":97,"gender":"Female","user_name":"fwhewill2o","organization":"Brainsphere","date":"2021-11-07 15:28:22","phone_number":"936-311-6619","children":97,"bvn":"2467927024","gurantor":"Carrissa Perell","gurantor_email":"fwhewill2o@cisco.com","user":"Fredra Whewill","user_email":"fwhewill2o@phpbb.com"},
    {"id":98,"gender":"Male","user_name":"fmoreno2p","organization":"Yozio","date":"2022-01-05 13:35:46","phone_number":"305-196-3088","children":98,"bvn":"1117380483","gurantor":"Weylin Franey","gurantor_email":"fmoreno2p@hibu.com","user":"Fair Moreno","user_email":"fmoreno2p@gov.uk"},
    {"id":99,"gender":"Female","user_name":"pcalton2q","organization":"Chatterpoint","date":"2021-11-21 20:38:04","phone_number":"909-449-0977","children":99,"bvn":"2493242149","gurantor":"Lynda Backwell","gurantor_email":"pcalton2q@admin.ch","user":"Phebe Calton","user_email":"pcalton2q@tiny.cc"},
    {"id":100,"gender":"Male","user_name":"wrotge2r","organization":"Chatterpoint","date":"2022-04-29 08:01:48","phone_number":"762-874-9884","children":100,"bvn":"1331851742","gurantor":"Jose Shardlow","gurantor_email":"wrotge2r@cmu.edu","user":"Wally Rotge","user_email":"wrotge2r@csmonitor.com"},
    {"id":101,"gender":"Female","user_name":"dwhitnall2s","organization":"Kanoodle","date":"2022-02-10 10:19:17","phone_number":"790-855-7805","children":101,"bvn":"0865591377","gurantor":"Merrie Vitet","gurantor_email":"dwhitnall2s@google.com.hk","user":"Dael Whitnall","user_email":"dwhitnall2s@cafepress.com"}]